{"type":"FeatureCollection","features":[{"type":"Feature","id":4,"geometry":{"type":"Point","coordinates":[-97.742892999999981,30.267175000000066]},"properties":{"OID":4,"Company":"Dell","Data_Center_Location":"Round Rock, Texas","Data_Generated_Per_Day__TB_":20,"Data_Equivalent__DVDs_":20000,"Latitude":30.267175000000002,"Longitude":-97.742892999999995,"Number_of_countries_served":"150+","Continents_served":"Americas, Europe, Asia","DDLat":30.267175000000002,"DDLon":-97.742892999999995,"Location":"Round Rock, Texas"}}]}